mcdbot/__init__.py
mcdbot/__main__.py
mcdbot/command.py
mcdbot/commands/__init__.py
mcdbot/commands/help_text.py
mcdbot/commands/register.py
mcdbot/commands/start.py
mcdbot/commands/unavailiable_in_context.py
mcdbot/commands/unregister.py
mcdbot/config.py
mcdbot/discordcontext.py
mcdbot/errors/__init__.py
mcdbot/errors/http_like_errors.py
mcdbot/errors/mcdbot_error.py
mcdbot/errors/mojang.py
mcdbot/errors/object_errors.py
mcdbot/errors/password_errors.py
mcdbot/helpers.py
mcdbot/logging_integration.py
mcdbot/mcdbot.py
mcdbot/mojang_api.py
mcdbot/rcon.py
mcdbot/redis.py
mcdbot/redis_migrate.py
mcdbot/uuid.py
mcdbot/whitelist.py
mcdbot-0.4.7.dist-info/LICENSE.txt
mcdbot-0.4.7.dist-info/WHEEL
mcdbot-0.4.7.dist-info/METADATA
mcdbot-0.4.7.dist-info/RECORD
