Metadata-Version: 2.1
Name: mcdbot
Version: 0.4.7
Summary: My PERSONAL project for connecting Discord communities with their Minecraft servers - WIP! NO DOCUMENTATION!
Home-page: https://gitlab.com/jsmetana/mcdbot
License: MPL-2.0
Author: Jakub Smetana
Author-email: jakub@smetana.ml
Requires-Python: >=3.6,<4.0
Classifier: License :: OSI Approved
Classifier: Programming Language :: Python :: 3
Classifier: Programming Language :: Python :: 3.6
Classifier: Programming Language :: Python :: 3.7
Classifier: Programming Language :: Python :: 3.8
Requires-Dist: aiofile (>=3.1.1,<4.0.0)
Requires-Dist: aioredis (>=1.3.1,<2.0.0)
Requires-Dist: asyncrcon (>=1.1.4,<2.0.0)
Requires-Dist: discord.py (>=1.5.0,<2.0.0)
Requires-Dist: loguru (>=0.5.3,<0.6.0)
Project-URL: Repository, https://gitlab.com/jsmetana/mcdbot
